<?xml version="1.0" encoding="UTF-8"?>
<listing xmlns:xsi="http://www.w3.org/2001/XMLSchema-instance" xsi:noNamespaceSchemaLocation="urn:magento:module:Magento_Ui:etc/ui_configuration.xsd">
    <settings>
        <buttons>
            <button name="export_regular_product">
                <url path="ecomm_priceengine/product/regularproduct"/>
                <label translate="true">Export Regular Product</label>
                <class>action-secondary</class>
            </button>
            <button name="export_shortdated_product">
                <url path="ecomm_priceengine/product/Shortdatedproduct"/>
                <label translate="true">Export Shortdated Product</label>
                <class>action-secondary</class>
            </button>
        </buttons>
    </settings>
</listing>